setup.py
emoji/__init__.py
emoji/emoji_utils.py
emoji_utils.egg-info/PKG-INFO
emoji_utils.egg-info/SOURCES.txt
emoji_utils.egg-info/dependency_links.txt
emoji_utils.egg-info/top_level.txt