Metadata-Version: 1.1
Name: emoji-utils
Version: 0.0.2
Summary: remove emojis from string, as description, comment and etc.
Home-page: UNKNOWN
Author: fanjun
Author-email: handsomefun@126.com
License: BSD License
Platform: linux ucs2
Classifier: Development Status :: 4 - Beta
Classifier: Operating System :: OS Independent
Classifier: Intended Audience :: Developers
Classifier: License :: OSI Approved :: BSD License
Classifier: Programming Language :: Python
Classifier: Programming Language :: Python :: Implementation
Classifier: Programming Language :: Python :: 2
Classifier: Programming Language :: Python :: 2.7
Classifier: Topic :: Software Development :: Libraries
